LICENSE
README.md
setup.cfg
setup.py
halc/__about__.py
halc/__init__.py
halc/initialize.py
halc/utils.py
halc.egg-info/PKG-INFO
halc.egg-info/SOURCES.txt
halc.egg-info/dependency_links.txt
halc.egg-info/requires.txt
halc.egg-info/top_level.txt
halc/coco/__init__.py
halc/coco/parse.py
halc/images/__init__.py
halc/images/get.py
halc/projects/__init__.py
halc/projects/create.py
halc/projects/delete.py
halc/projects/get.py
halc/storage/__init__.py
halc/storage/create.py
halc/storage/delete.py
halc/storage/get.py
halc/upload/__init__.py
halc/upload/images.py
halc/upload/labels.py
halc/versions/__init__.py
halc/versions/create.py
halc/versions/delete.py
halc/versions/get.py