Metadata-Version: 2.1
Name: halc
Version: 0.22.5
Summary: Python SDK for Happyrobot's HALC
Home-page: https://happyrobot.ai
Author: Happyrobot
Author-email: luis.paarup@happyrobot.ai
License: MIT
Keywords: happyrobot computer vision artificial intelligence foundation models large vision
Classifier: Development Status :: 3 - Alpha
Classifier: Intended Audience :: Developers
Classifier: Topic :: Software Development :: Build Tools
Classifier: Programming Language :: Python :: 3
Classifier: Programming Language :: Python :: 3.5
Classifier: Programming Language :: Python :: 3.6
Classifier: Programming Language :: Python :: 3.7
Classifier: Programming Language :: Python :: 3.9
Classifier: License :: OSI Approved :: MIT License
Requires-Python: >=3.5
License-File: LICENSE
